steamwebtools.py
steam_web_tools-1.1.dist-info/LICENSE
steam_web_tools-1.1.dist-info/METADATA
steam_web_tools-1.1.dist-info/WHEEL
steam_web_tools-1.1.dist-info/top_level.txt
steam_web_tools-1.1.dist-info/RECORD
